dactyl_generation/__init__.py
dactyl_generation/anthropic_generation.py
dactyl_generation/bedrock_generation.py
dactyl_generation/constants.py
dactyl_generation/deepseek_generation.py
dactyl_generation/google_generation.py
dactyl_generation/mistral_generation.py
dactyl_generation/openai_generation.py
dactyl_generation/quick.py
dactyl_generation-1.0.0.dist-info/licenses/LICENSE
dactyl_generation-1.0.0.dist-info/METADATA
dactyl_generation-1.0.0.dist-info/WHEEL
dactyl_generation-1.0.0.dist-info/top_level.txt
dactyl_generation-1.0.0.dist-info/RECORD
