Metadata-Version: 2.4
Name: dactyl_generation
Version: 1.0.0
Summary: LLM helper package to generate AI-generated texts.
Author: Shantanu Thorat
License: MIT
Classifier: Programming Language :: Python :: 3
Classifier: Operating System :: OS Independent
Requires-Python: >=3.9
License-File: LICENSE
Requires-Dist: anthropic
Requires-Dist: litellm
Requires-Dist: mistralai
Requires-Dist: numpy==1.26.4
Requires-Dist: openai
Requires-Dist: pandas
Requires-Dist: protobuf
Requires-Dist: python-dotenv
Requires-Dist: Requests
Requires-Dist: tqdm
Requires-Dist: typing_extensions
Requires-Dist: google-generativeai
Requires-Dist: boto3
Dynamic: license-file
